{
    "Title": "\u8a0a\u606f",
    "Modules": [
        {
            "Sections": [
                {
                    "Description": "\u8a0a\u606f\u4e2d\u7684\u95dc\u9589\u6309\u9215\u9810\u8a2d\u4e26\u6c92\u6709\u52d5\u4f5c\uff0c\u50c5\u662f\u88dd\u98fe\u800c\u5df2\u3002\u4f46\u662f\u4f60\u53ef\u4ee5\u900f\u904e JavaScript \u5c07\u8a72\u6309\u9215\u5957\u4e0a\u4e00\u500b\u95dc\u9589\u8a0a\u606f\u7684\u52d5\u4f5c\u3002",
                    "JavaScript": "ts('.dismissable.message').message()\n",
                    "AutoExecute": true,
                    "Title": "\u53ef\u95dc\u9589\u7684",
                    "HTML": "<div class=\"ts [[dismissable]] message\">\n    <button class=\"ts close {{button}}\"></button>\n    <div class=\"header\">\n        \u4e0d\u559c\u6b61\u6211\uff1f\n    </div>\n    <p>\u90a3\u5c31\u95dc\u9589\u6211\u5427\u3002</p>\n</div>\n",
                    "Since": "2.3.3"
                }
            ],
            "Title": "JavaScript",
            "Description": "\u8a0a\u606f\u6709\u63d0\u4f9b\u53ef\u7528\u7684 JavaScript \u6a21\u584a\u3002"
        }
    ],
    "Description": "\u50b3\u905e\u8a0a\u606f\u81f3\u9060\u65b9\u3002",
    "Definitions": [
        {
            "Sections": [
                {
                    "Title": "\u8a0a\u606f",
                    "Description": "\u4e00\u500b\u6700\u57fa\u672c\u7684\u8a0a\u606f\u3002",
                    "Since": "2.3.3",
                    "HTML": "<div class=\"ts [[message]]\">\n    <div class=\"header\">\u975c\u601d\u8a9e</div>\n    <p>\u8f38\u7684\u6642\u5019\u5931\u53bb\u6700\u591a\u7684\u5c31\u662f\u7406\u667a\u3002</p>\n</div>\n"
                },
                {
                    "Title": "\u57fa\u672c",
                    "Description": "\u8a0a\u606f\u53ef\u4ee5\u53ea\u7559\u4e0b\u57fa\u672c\u7d50\u69cb\u3002",
                    "Since": "2.3.3",
                    "HTML": "<div class=\"ts [[basic]] message\">\n    \u76f4\u5230\u4f60\u6210\u529f\u4e4b\u524d\uff0c\u4eba\u5011\u90fd\u662f\u778e\u5b50\u3002\n</div>\n"
                },
                {
                    "Title": "\u5916\u6846\u7dda",
                    "Description": "\u8a0a\u606f\u53ef\u4ee5\u53ea\u6709\u5916\u6846\u7dda\u3002",
                    "Since": "2.3.3",
                    "HTML": "<div class=\"ts [[outlined]] message\">\n    \u76f4\u5230\u4f60\u6210\u529f\u4e4b\u524d\uff0c\u4eba\u5011\u90fd\u662f\u778e\u5b50\u3002\n</div>\n"
                },
                {
                    "Title": "\u7d50\u69cb\u5316",
                    "Description": "\u8a0a\u606f\u80fd\u5920\u770b\u8d77\u4f86\u66f4\u5177\u6709\u7d50\u69cb\uff0c\u4e26\u5e36\u6709\u66f4\u591a\u9644\u52a0\u52d5\u4f5c\u3002",
                    "Since": "2.3.3",
                    "HTML": "<div class=\"ts [[structured]] message\">\n    <div class=\"avatar\">\n        <img src=\"!-user-!\">\n    </div>\n    <div class=\"content\">\n        <div class=\"description\">\n            <p>\u6709\u4f4d\u4f7f\u7528\u8005\u8dd1\u5230\u4e86\u4f60\u7684\u5c0f\u5c4b\u4e26\u5411\u4f60\u9053\u8072\u65e9\u5b89\uff0c</p>\n            <p>\u4f46\u5c31\u5728\u4f60\u5378\u4e0b\u5fc3\u9632\u7684\u540c\u6642\uff0c\u4f60\u610f\u8b58\u5230\u6709\u4ec0\u9ebc\u6771\u897f\u5f9e\u8eab\u908a\u6d88\u5931\u4e86\u3002</p>\n        </div>\n        <div class=\"actions\">\n            <a class=\"primary\" href=\"#!\">\u6aa2\u67e5\u9053\u5177\u6b04</a>\n            <a href=\"#!\">\u53eb\u4f4f\u5c0d\u65b9</a>\n        </div>\n    </div>\n</div>\n"
                },
                {
                    "Title": "\u8a9e\u6c23",
                    "Description": "\u8a0a\u606f\u4e5f\u53ef\u4ee5\u5e36\u6709\u4e0d\u540c\u7684\u8a9e\u6c23\u3002",
                    "Since": "2.3.3",
                    "HTML": "<div class=\"ts [[primary]] message\">\n    <div class=\"header\">\u73fe\u5df2\u958b\u59cb</div>\n    <p>\u76ee\u524d\u300cosu! World Cup 2015\u300d\u5df2\u958b\u59cb\u9032\u884c\u76f4\u64ad\u3002</p>\n</div>\n<div class=\"ts [[warning]] message\">\n    <div class=\"header\">\u60a8\u9700\u8981\u5148\u767b\u5165\uff01</div>\n    <p>\u4e0d\u597d\u610f\u601d\uff0c\u60a8\u9700\u8981\u5148\u767b\u5165\u624d\u80fd\u5920\u57f7\u884c\u9019\u9805\u52d5\u4f5c\u3002</p>\n</div>\n<div class=\"ts [[info]] message\">\n    <div class=\"header\">\u9700\u8981\u4e00\u4e9b\u6642\u9593</div>\n    <p>\u4f60\u6240\u4e0a\u50b3\u7684\u5f71\u7247\u6703\u5728\u7a0d\u5f8c\u958b\u59cb\u9032\u884c\u8f49\u6a94\u52d5\u4f5c\u3002</p>\n</div>\n"
                },
                {
                    "Title": "\u80af\u5b9a\u548c\u5426\u5b9a",
                    "Description": "\u8a0a\u606f\u53ef\u4ee5\u6709\u80af\u5b9a\u6216\u662f\u5426\u5b9a\u7684\u8a9e\u6c23\u3002",
                    "Since": "2.3.3",
                    "HTML": "<div class=\"ts [[positive]] message\">\n    <div class=\"header\">\u606d\u559c\uff01</div>\n    <p>\u4f60\u5df2\u7d93\u8a3b\u518a\u6210\u529f\u3002</p>\n</div>\n<div class=\"ts [[negative]] message\">\n    <div class=\"header\">\u6b64\u6587\u7ae0\u5df2\u88ab\u522a\u9664</div>\n    <p>\u4f60\u6b32\u62dc\u8a2a\u7684\u6587\u7ae0\u56e0\u9055\u53cd\u898f\u5b9a\u800c\u906d\u5230\u522a\u9664\u3002</p>\n</div>\n"
                },
                {
                    "Title": "\u53cd\u8272",
                    "Description": "\u53cd\u8272\u8a9e\u6c23\u53ef\u4ee5\u7528\u5728\u8a0a\u606f\u4e0a\u3002",
                    "Since": "2.3.3",
                    "HTML": "<div class=\"ts [[inverted]] message\">\n    <div class=\"header\">\u7cfb\u7d71\u5347\u7d1a\u4e2d</div>\n    <p>\u642d\u5566\u5566\uff01\u7cfb\u7d71\u6b63\u5728\u5347\u7d1a\uff01</p>\n</div>\n<div class=\"ts [[inverted]] primary message\">\n    <div class=\"header\">\u73fe\u5df2\u958b\u59cb</div>\n    <p>\u76ee\u524d\u300cosu! World Cup 2015\u300d\u5df2\u958b\u59cb\u9032\u884c\u76f4\u64ad\u3002</p>\n</div>\n<div class=\"ts [[inverted]] warning message\">\n    <div class=\"header\">\u60a8\u9700\u8981\u5148\u767b\u5165\uff01</div>\n    <p>\u4e0d\u597d\u610f\u601d\uff0c\u60a8\u9700\u8981\u5148\u767b\u5165\u624d\u80fd\u5920\u57f7\u884c\u9019\u9805\u52d5\u4f5c\u3002</p>\n</div>\n<div class=\"ts [[inverted]] info message\">\n    <div class=\"header\">\u9700\u8981\u4e00\u4e9b\u6642\u9593</div>\n    <p>\u4f60\u6240\u4e0a\u50b3\u7684\u5f71\u7247\u6703\u5728\u7a0d\u5f8c\u958b\u59cb\u9032\u884c\u8f49\u6a94\u52d5\u4f5c\u3002</p>\n</div>\n<div class=\"ts [[inverted]] positive message\">\n    <div class=\"header\">\u606d\u559c\uff01</div>\n    <p>\u4f60\u5df2\u7d93\u8a3b\u518a\u6210\u529f\u3002</p>\n</div>\n<div class=\"ts [[inverted]] negative message\">\n    <div class=\"header\">\u6b64\u6587\u7ae0\u5df2\u88ab\u522a\u9664</div>\n    <p>\u4f60\u6b32\u62dc\u8a2a\u7684\u6587\u7ae0\u56e0\u9055\u53cd\u898f\u5b9a\u800c\u906d\u5230\u522a\u9664\u3002</p>\n</div>\n"
                },
                {
                    "Title": "\u6b21\u8981",
                    "Description": "\u8a0a\u606f\u7684\u91cd\u8981\u7a0b\u5ea6\u53ef\u4ee5\u662f\u6b21\u8981\u7684\u3002",
                    "Since": "2.3.3",
                    "HTML": "<div class=\"ts [[secondary]] message\">\n    <div class=\"header\">\u7cfb\u7d71\u5347\u7d1a\u4e2d</div>\n    <p>\u642d\u5566\u5566\uff01\u7cfb\u7d71\u6b63\u5728\u5347\u7d1a\uff01</p>\n</div>\n<div class=\"ts [[secondary]] primary message\">\n    <div class=\"header\">\u73fe\u5df2\u958b\u59cb</div>\n    <p>\u76ee\u524d\u300cosu! World Cup 2015\u300d\u5df2\u958b\u59cb\u9032\u884c\u76f4\u64ad\u3002</p>\n</div>\n<div class=\"ts [[secondary]] inverted positive message\">\n    <div class=\"header\">\u606d\u559c\uff01</div>\n    <p>\u4f60\u5df2\u7d93\u8a3b\u518a\u6210\u529f\u3002</p>\n</div>\n<div class=\"ts [[secondary]] inverted negative message\">\n    <div class=\"header\">\u6b64\u6587\u7ae0\u5df2\u88ab\u522a\u9664</div>\n    <p>\u4f60\u6b32\u62dc\u8a2a\u7684\u6587\u7ae0\u56e0\u9055\u53cd\u898f\u5b9a\u800c\u906d\u5230\u522a\u9664\u3002</p>\n</div>\n"
                },
                {
                    "Title": "\u6e05\u55ae",
                    "Description": "\u4e00\u500b\u5e36\u6709\u6e05\u55ae\u7684\u8a0a\u606f\u3002",
                    "Since": "2.3.3",
                    "HTML": "<div class=\"ts message\">\n    <div class=\"header\">\u73fe\u5df2\u63a8\u51fa</div>\n    <[[ul]]>\n        <li>\u865b\u64ec\u5be6\u5883\u64f4\u5145</li>\n        <li>\u80a5\u5b85\u6a21\u64ec\u5668 2016</li>\n    </[[ul]]>\n</div>\n"
                },
                {
                    "Title": "\u5716\u793a",
                    "Description": "\u4e00\u500b\u5e36\u6709\u5716\u793a\u7684\u8a0a\u606f\u3002",
                    "Since": "2.3.3",
                    "HTML": "<div class=\"ts [[icon]] message\">\n    <i class=\"gift {{icon}}\"></i>\n    <div class=\"content\">\n        <div class=\"header\">\u6700\u65b0\u79ae\u7269</div>\n        <p>\u4f60\u6536\u5230\u4e86\u4f86\u81ea ThisAV \u7684\u79ae\u7269\u3002</p>\n    </div>\n</div>\n"
                },
                {
                    "Title": "\u53ef\u95dc\u9589\u7684",
                    "Description": "\u4f60\u80fd\u5920\u5728\u8a0a\u606f\u5167\u64fa\u653e\u4e00\u500b\u95dc\u9589\u6309\u9215\uff0c\u4ee4\u8a0a\u606f\u770b\u8d77\u4f86\u50cf\u53ef\u95dc\u9589\u4e00\u6a23\u3002\u82e5\u771f\u8981\u57f7\u884c\u95dc\u9589\u52d5\u4f5c\uff0c\u8acb\u53c3\u8003 JavaScript \u6a21\u584a\u7ae0\u7bc0\u3002",
                    "Since": "2.3.3",
                    "HTML": "<div class=\"ts [[dismissable]] message\">\n    <button class=\"ts close {{button}}\"></button>\n    <div class=\"header\">\n        \u4e0d\u559c\u6b61\u6211\uff1f\n    </div>\n    <p>\u90a3\u5c31\u95dc\u9589\u6211\u5427\u3002</p>\n</div>\n"
                }
            ],
            "Title": "\u7a2e\u985e",
            "Description": "\u9078\u55ae\u5177\u6709\u4e0d\u540c\u7684\u7a2e\u985e\u3002"
        },
        {
            "Sections": [
                {
                    "Title": "\u96b1\u85cf",
                    "Description": "\u7528\u4f86\u96b1\u85cf\u8a0a\u606f\u3002",
                    "Since": "2.3.3",
                    "HTML": "<div class=\"ts [[hidden]] message\">\n    \u4f60\u770b\u4e0d\u898b\u6211\u3002\n</div>\n"
                }
            ],
            "Title": "\u72c0\u614b",
            "Description": "\u8a0a\u606f\u5e36\u6709\u4e00\u4e9b\u4e0d\u540c\u7684\u72c0\u614b\u3002"
        },
        {
            "Sections": [
                {
                    "Title": "\u8a3b\u91cb",
                    "Description": "\u8a0a\u606f\u88e1\u53ef\u4ee5\u64fa\u653e\u57fa\u672c\u7684\u6587\u5b57\u8a3b\u91cb\uff0c\u9019\u53ea\u7528\u65bc\u7d50\u69cb\u8f03\u8907\u96dc\u7684\u8a0a\u606f\uff0c\u901a\u5e38\u4f60\u4e0d\u9700\u8981\u9019\u9ebc\u505a\u3002",
                    "Since": "2.3.3",
                    "HTML": "<div class=\"ts message\">\n    <div class=\"content\">\n        <div class=\"[[description]]\">\n            \u96d6\u7136\u958b\u59cb\u662f\u4e00\u6a23\u7684\uff0c\u4f46\u7d93\u6b77\u4ee4\u6211\u5011\u6210\u70ba\u4e86\u4e0d\u540c\u4eba\u3002\n        </div>\n    </div>\n</div>\n"
                },
                {
                    "Title": "\u984d\u5916\u8a3b\u91cb",
                    "Description": "\u4e00\u500b\u8207\u9019\u500b\u8a0a\u606f\u6709\u95dc\u9023\u7684\u984d\u5916\u5167\u5bb9\u3002",
                    "Since": "2.3.3",
                    "HTML": "<div class=\"ts structured message\">\n    <div class=\"content\">\n        <div class=\"description\">\n            \u60a8\u5df2\u7372\u5f97 iPhone 9S \u62bd\u734e\u6a5f\u6703\uff01\u4f46\u662f\u4f60\u6c38\u9060\u90fd\u4e0d\u6703\u4e2d\u734e\uff0c\u6211\u5011\u5f88\u671f\u5f85\u60a8\u7684\u53c3\u8207\u3002\n        </div>\n        <div class=\"[[extra description]]\">\n            \u6ce8\u610f\uff0c\u4f60\u53ea\u6709\u4e09\u5341\u79d2\u7684\u9078\u64c7\u6a5f\u6703\uff01\n        </div>\n    </div>\n</div>\n"
                },
                {
                    "Title": "\u52d5\u4f5c",
                    "Description": "\u4f60\u80fd\u5920\u5728\u8a0a\u606f\u7684\u53f3\u5074\u5b89\u63d2\u4e00\u4e9b\u52d5\u4f5c\u6309\u9215\u3002",
                    "Since": "2.3.3",
                    "HTML": "<div class=\"ts message\">\n    <div class=\"content\">\n        <div class=\"description\">\n            \u6211\u5011\u5df2\u63a5\u7372\u7248\u6b0a\u8b66\u544a\u4e26\u5c07\u6b64\u5f71\u7247\u9032\u884c\u6d88\u97f3\u8655\u7406\uff0c\u9019\u53ef\u80fd\u5c0e\u81f4\u4f60\u7684\u5f71\u7247\u89c0\u770b\u6b21\u6578\u4e0b\u964d\u3002\n        </div>\n        <div class=\"[[actions]]\">\n            <button class=\"ts small inverted basic negative {{button}}\">\u91cd\u65b0\u4e0a\u8a34</button>\n        </div>\n    </div>\n</div>\n"
                },
                {
                    "Title": "\u5716\u793a",
                    "Description": "\u7d50\u69cb\u5316\u7684\u8a0a\u606f\u5167\u53ef\u4ee5\u64fa\u653e\u5716\u793a\u3002",
                    "Since": "2.3.3",
                    "HTML": "<div class=\"ts structured message\">\n    <div class=\"[[icon]]\">\n        <i class=\"trash {{icon}}\"></i>\n    </div>\n    <div class=\"content\">\n        <div class=\"description\">\n            \u4f60\u5df2\u6210\u529f\u5730\u5c07\u6587\u7ae0\u79fb\u52d5\u81f3\u5783\u573e\u6876\u4e86\u3002\n        </div>\n        <div class=\"actions\">\n            <a href=\"#!\">\u9084\u539f\u6587\u7ae0</a>\n        </div>\n    </div>\n</div>\n"
                },
                {
                    "Title": "\u982d\u50cf",
                    "Description": "\u8a0a\u606f\u88e1\u4e5f\u80fd\u5920\u64fa\u7f6e\u4e00\u500b\u4f7f\u7528\u8005\u982d\u50cf\u3002",
                    "Since": "2.3.3",
                    "HTML": "<div class=\"ts structured message\">\n    <div class=\"[[avatar]]\">\n        <img src=\"!-user-!\">\n    </div>\n    <div class=\"content\">\n        <div class=\"description\">\n            \u4f60\u7684\u670b\u53cb\u525b\u624d\u5728\u4f60\u7684\u6587\u7ae0\u4e2d\u7559\u8a00\u3002\n        </div>\n        <div class=\"actions\">\n            <a class=\"primary\" href=\"#!\">\u67e5\u770b</a>\n            <a href=\"#!\">\u4e0b\u6b21\u5225\u63d0\u9192\u6211</a>\n        </div>\n    </div>\n</div>\n"
                }
            ],
            "Title": "\u5167\u5bb9",
            "Description": "\u8a0a\u606f\u88e1\u9762\u53ef\u4ee5\u5e36\u6709\u4e0d\u540c\u7684\u5167\u5bb9\u3002"
        },
        {
            "Sections": [
                {
                    "Title": "\u7e2e\u6e1b\u7248",
                    "Description": "\u8b93\u8a0a\u606f\u900f\u904e\u6587\u5b57\u9577\u5ea6\u4f86\u6c7a\u5b9a\u5bec\u5ea6\u3002",
                    "Since": "2.3.3",
                    "HTML": "<div class=\"ts [[compact]] message\">\n    \u53ef\u60e1\uff0c\u597d\u60f3\u77e5\u9053\u5979\u7684\u540d\u5b57\u554a\uff01\n</div>\n"
                },
                {
                    "Title": "\u6de1\u5316",
                    "Description": "\u8a0a\u606f\u53ef\u4ee5\u88ab\u6de1\u5316\u3002",
                    "Since": "2.3.3",
                    "HTML": "<div class=\"ts [[faded]] message\">\n    \u7576\u4f60\u63a5\u53d7\u4e86\u73fe\u6cc1\uff0c\u5c31\u7b49\u65bc\u63a5\u53d7\u4e86\u6b7b\u4ea1\u3002\n</div>\n"
                },
                {
                    "Title": "\u7e2e\u6e1b",
                    "Description": "\u8a0a\u606f\u7684\u5167\u8ddd\u53ef\u4ee5\u7701\u53bb\u3002",
                    "Since": "2.3.3",
                    "HTML": "<div class=\"ts [[fitted]] message\">\n    \u9019\u500b\u8a0a\u606f\u6c92\u6709\u5167\u8ddd\u3002\n</div>\n<div class=\"ts [[horizontally fitted]] message\">\n    \u79fb\u9664\u6c34\u5e73\u5167\u8ddd\u3002\n</div>\n<div class=\"ts [[vertically fitted]] message\">\n    \u9019\u500b\u8a0a\u606f\u6c92\u6709\u5782\u76f4\u5167\u8ddd\u3002\n</div>\n"
                },
                {
                    "Title": "\u7121\u908a\u6846",
                    "Description": "\u8a0a\u606f\u53ef\u4ee5\u6c92\u6709\u908a\u6846\u3002",
                    "Since": "2.3.3",
                    "HTML": "<div class=\"ts [[borderless]] message\">\n    \u9019\u500b\u8a0a\u606f\u6c92\u6709\u908a\u6846\u3002\n</div>\n"
                },
                {
                    "Title": "\u9644\u8457",
                    "Remove": [
                        "<br><br>"
                    ],
                    "Description": "\u8a0a\u606f\u53ef\u4ee5\u9644\u8457\u5728\u5176\u4ed6\u5143\u7d20\u4e0a\u4e0b\u3002",
                    "Since": "2.3.3",
                    "HTML": "<div class=\"ts padded [[top attached]] message\">\n    <div class=\"header\">\n        \u6b63\u5728\u7de8\u8f2f\uff1a\u95dc\u65bc\u6211\n    </div>\n    <p>\u8acb\u6aa2\u67e5\u4ee5\u4e0b\u300c\u95dc\u65bc\u6211\u300d\u662f\u5426\u6b63\u78ba\u3002</p>\n</div>\n<div class=\"ts attached {{segment}}\">\n    \u59cb\u6625\u5230\u5e95\u662f\u4ec0\u9ebc\uff1f\u59cb\u6625\uff0c\u7d55\u4e0d\u5411\u65e5\u66c6\u59a5\u5354\u59cb\u6625\uff0c\u7d55\u4e0d\u5411\u9810\u544a\u4f4e\u982d\u53ea\u8981 CM3D2 \u5728\u624b\uff0c\u5c31\u80fd\u5920\u6c38\u9060\u5730\u59cb\u6625\u59cb\u6625\u662f\u4e00\u7a2e\u7cbe\u795e\uff0c\u4e00\u7a2e\u614b\u5ea6\u4e00\u7a2e\u9769\u547d\uff0c\u4e00\u7a2e\u53db\u9006\u3002\u65bc\u662f\u6211\u4e86\u89e3\u300c\u8df3\u7968\u3001\u5ef6\u671f\u3001\u4e09\u87a2\u5e55\uff0c\u9019\u5c31\u662f\u59cb\u6625\u3002\u300d\n</div>\n<div class=\"ts positive [[attached]] message\">\n    \u4ee5\u4e0b\u662f\u5df2\u6838\u51c6\u5167\u5bb9\u3002\n</div>\n<div class=\"ts bottom attached {{segment}}\">\n    \u590f\u5e0c\u662f\u4e00\u500b\u57fa\u65bc PHP \u7684\u6642\u9593\u985e\u5225\uff0c \u7528\u4ee5\u53d6\u5f97\u73fe\u5728\u7684\u6642\u9593\uff0c\u6216\u8005\u662f\u6578\u5929\u5f8c\u7684\u73fe\u5728\u6642\u523b\u3002\n</div>\n<br><br>\n<div class=\"ts fluid top attached {{input}}\">\n    <input type=\"text\" placeholder=\"\u76e3\u8b77\u4eba\u59d3\u540d\">\n</div>\n<div class=\"ts warning [[bottom attached]] message\">\n    \u7576\u6709\u76e3\u8b77\u4eba\u6642\u8acb\u586b\u5beb\u6b64\u6b04\u4f4d\u3002\n</div>\n"
                },
                {
                    "Title": "\u9644\u8457\u589e\u52a0\u5167\u8ddd",
                    "Description": "\u8a0a\u606f\u5728\u9644\u8457\u7684\u60c5\u6cc1\u4e0b\u6703\u7e2e\u6e1b\u5167\u8ddd\u4ee5\u907f\u514d\u904e\u5927\uff0c\u9019\u500b\u6642\u5019\u4f60\u80fd\u5920\u589e\u52a0\u5167\u8ddd\u4f86\u4ee4\u8a0a\u606f\u5927\u65bc\u4ed6\u5011\u6240\u9644\u8457\u7684\u5143\u7d20\u3002",
                    "Since": "2.3.3",
                    "HTML": "<div class=\"ts top attached message\">\n    \u57fa\u672c\u5167\u8ddd\n</div>\n<div class=\"ts attached {{segment}}\">\n    \u6587\u5b57\u3002\n</div>\n<div class=\"ts [[padded]] attached message\">\n    \u589e\u52a0\u5167\u8ddd\n</div>\n<div class=\"ts attached {{segment}}\">\n    \u6587\u5b57\u3002\n</div>\n<div class=\"ts [[very padded]] bottom attached message\">\n    \u8d85\u7d1a\u5167\u8ddd\n</div>\n"
                },
                {
                    "Title": "\u6c34\u5e73\u5c0d\u9f4a",
                    "Description": "\u4f60\u53ef\u4ee5\u6539\u8b8a\u8a0a\u606f\u4e2d\u7684\u6587\u5b57\u6c34\u5e73\u5c0d\u9f4a\uff0c\u4f8b\u5982\u7f6e\u5de6\u3001\u7f6e\u53f3\u3001\u6216\u7f6e\u4e2d\u3002",
                    "Since": "2.3.3",
                    "HTML": "<div class=\"ts [[left aligned]] message\">\n    \u6211\u7f6e\u5de6\u5c0d\u9f4a\u3002\n</div>\n<div class=\"ts [[center aligned]] message\">\n    \u6211\u7f6e\u4e2d\u5c0d\u9f4a\u3002\n</div>\n<div class=\"ts [[right aligned]] message\">\n    \u6211\u7f6e\u53f3\u5c0d\u9f4a\u3002\n</div>\n"
                },
                {
                    "Title": "\u6f02\u6d6e",
                    "Description": "\u8a0a\u606f\u53ef\u4ee5\u770b\u8d77\u4f86\u662f\u88ab\u8209\u8d77\u3001\u6f02\u6d6e\u7684\u3002",
                    "Since": "2.3.3",
                    "HTML": "<div class=\"ts [[floating]] message\">\n    \u6211\u597d\u50cf\u88ab\u8209\u8d77\u4f86\u4e86\u3002\n</div>\n"
                },
                {
                    "Title": "\u5c3a\u5bf8",
                    "Description": "\u8a0a\u606f\u6709\u63d0\u4f9b\u591a\u7a2e\u5c3a\u5bf8\u3002",
                    "Since": "2.3.3",
                    "HTML": "<div class=\"ts [[mini]] message\">\n    \u8ff7\u4f60\n</div>\n<div class=\"ts [[tiny]] message\">\n    \u5fae\u5c0f\n</div>\n<div class=\"ts [[small]] message\">\n    \u5c0f\u7684\n</div>\n<div class=\"ts [[medium]] message\">\n    \u9069\u4e2d\n</div>\n<div class=\"ts [[large]] message\">\n    \u5927\u7684\n</div>\n<div class=\"ts [[big]] message\">\n    \u5927\u578b\n</div>\n<div class=\"ts [[huge]] message\">\n    \u5de8\u5927\n</div>\n<div class=\"ts [[massive]] message\">\n    \u91cd\u91cf\u7d1a\n</div>\n"
                }
            ],
            "Title": "\u5916\u89c0",
            "Description": "\u8a0a\u606f\u6709\u4e0d\u540c\u7684\u5916\u89c0\u3002"
        }
    ]
}